{
  "loanApplicants": [
    {
      "email": "rukeeojigbo@gmail.com",
      "mobile": "08183840096",
      "bvn": "123244",
      "dateOfBirth": "nov-3rd-21000",
      "password": "beautifulUju",
      "id": 1
    },
    {
      "email": "seyimils",
      "mobile": "xxxxxxxx",
      "bvn": "xxxxx",
      "dateOfBirth": "2019-02-08",
      "password": "xxxxx",
      "id": 2
    },
    {
      "email": "richardojigbo@gmail.com",
      "mobile": "09882",
      "bvn": "111111",
      "dateOfBirth": "2019-02-07",
      "password": "xxx",
      "id": 3
    },
    {
      "email": "okonojigbo@gmail.com",
      "mobile": "123",
      "bvn": "123",
      "dateOfBirth": "2019-02-08",
      "password": "xxx",
      "id": 4
    },
    {
      "email": "rukeeojigbo@gmail.comm",
      "mobile": "08183840096",
      "bvn": "123412312",
      "dateOfBirth": "2019-02-15",
      "password": "xxxx",
      "id": 5
    },
    {
      "email": "seyinfagbamila@gmail.com",
      "mobile": "08183840096",
      "bvn": "2222222222",
      "dateOfBirth": "2019-02-24",
      "password": "rukee212",
      "id": 6
    },
    {
      "email": "rukeeojigbo@gmail.com",
      "mobile": "1234533",
      "bvn": "12321312312312",
      "dateOfBirth": "2019-03-31",
      "password": "xxxxx",
      "id": 7
    },
    {
      "email": "Oluwaseyi@gmail.com",
      "mobile": "08036687418",
      "bvn": "23232323423",
      "dateOfBirth": "2019-03-19",
      "password": "xxxxxxxx",
      "id": 8
    }
  ],
  "loanBucket": [
    {
      "email": "richardojigbo@gmail.com",
      "bvn": "204",
      "requestType": "for rent",
      "loanAmount": "6000",
      "status": "Approved",
      "id": 4
    },
    {
      "email": "cynthiaugorji@gmail.com",
      "bvn": "2456586",
      "requestType": "for make up",
      "loanAmount": "5000",
      "status": "under consideration",
      "id": 9
    },
    {
      "email": "richardojigbo@gmail.com",
      "bvn": "1111111",
      "requestType": "for Transportation",
      "loanAmount": "500",
      "status": "under consideration",
      "id": 13
    },
    {
      "email": "richardojigbo@gmail.com",
      "bvn": "8888888",
      "requestType": "for feeding ",
      "loanAmount": "589",
      "status": "under consideration",
      "id": 14
    },
    {
      "email": "rukeeojigbo@gmail.com",
      "bvn": "1111111",
      "requestType": "for house rent",
      "loanAmount": "500",
      "status": "Approved",
      "id": 15
    },
    {
      "email": "rukeeojigbo@gmail.com",
      "bvn": "1111111",
      "requestType": "for house",
      "loanAmount": "589",
      "status": "under consideration",
      "id": 17
    },
    {
      "email": "rukeeojigbo@gmail.com",
      "bvn": "8888888",
      "requestType": "for Transportation",
      "loanAmount": "500",
      "status": "under consideration",
      "id": 18
    },
    {
      "email": "Oluwaseyi@gmail.com",
      "bvn": "8888888",
      "requestType": "for Transportation",
      "loanAmount": "600",
      "status": "under consideration",
      "id": 19
    }
  ],
  "admin": [
    {
      "email": "admin@gmail.com",
      "password": "1234"
    }
  ]
}